setup.py
sshm/__init__.py
sshm/_info.py
sshm/lib.py
sshm/main.py
sshm.egg-info/PKG-INFO
sshm.egg-info/SOURCES.txt
sshm.egg-info/dependency_links.txt
sshm.egg-info/entry_points.txt
sshm.egg-info/requires.txt
sshm.egg-info/top_level.txt