Metadata-Version: 1.1
Name: sshm
Version: 1.5.1
Summary: SSH into multiple hosts.
Home-page: https://github.com/rolobio/sshm
Author: rolobio
Author-email: rolobio+sshm@rolobio.com
License: GNU GPL
Keywords: ssh multiple
Platform: UNKNOWN
Classifier: Development Status :: 5 - Production/Stable
Classifier: Topic :: Utilities
Classifier: License :: OSI Approved :: GNU General Public License (GPL)
